odoo/addons/currency_rate_update_RO_BNR/README.rst
odoo/addons/currency_rate_update_RO_BNR/__init__.py
odoo/addons/currency_rate_update_RO_BNR/__manifest__.py
odoo/addons/currency_rate_update_RO_BNR/i18n/currency_rate_update_RO_BNR.pot
odoo/addons/currency_rate_update_RO_BNR/models/__init__.py
odoo/addons/currency_rate_update_RO_BNR/models/res_currency_rate_provider_RO_BNR.py
odoo/addons/currency_rate_update_RO_BNR/readme/CONTRIBUTORS.rst
odoo/addons/currency_rate_update_RO_BNR/readme/DESCRIPTION.rst
odoo/addons/currency_rate_update_RO_BNR/readme/INSTALL.rst
odoo/addons/currency_rate_update_RO_BNR/readme/USAGE.rst
odoo/addons/currency_rate_update_RO_BNR/static/description/icon.png
odoo/addons/currency_rate_update_RO_BNR/static/description/index.html
odoo/addons/currency_rate_update_RO_BNR/tests/__init__.py
odoo/addons/currency_rate_update_RO_BNR/tests/nbrfxrates.xml
odoo/addons/currency_rate_update_RO_BNR/tests/nbrfxrates2022.xml
odoo/addons/currency_rate_update_RO_BNR/tests/nbrfxrates2023.xml
odoo/addons/currency_rate_update_RO_BNR/tests/nbrfxrates2024.xml
odoo/addons/currency_rate_update_RO_BNR/tests/test_currency_rate_update_ro_bnr.py
odoo/addons/currency_rate_update_RO_BNR/views/res_currency_rate.xml
odoo14_addon_currency_rate_update_RO_BNR-14.0.1.6.0.dist-info/METADATA
odoo14_addon_currency_rate_update_RO_BNR-14.0.1.6.0.dist-info/WHEEL
odoo14_addon_currency_rate_update_RO_BNR-14.0.1.6.0.dist-info/top_level.txt
odoo14_addon_currency_rate_update_RO_BNR-14.0.1.6.0.dist-info/RECORD
