Metadata-Version: 2.1
Name: odoo14-addon-currency-rate-update-RO-BNR
Version: 14.0.1.6.0
Summary: Currency Rate Update National Bank of Romania service
Home-page: https://github.com/OCA/l10n-romania
Author: NextERP Romania,Forest and Biomass Romania,Odoo Community Association (OCA)
Author-email: support@odoo-community.org
License: AGPL-3
Platform: UNKNOWN
Classifier: Programming Language :: Python
Classifier: Framework :: Odoo
Classifier: Framework :: Odoo :: 14.0
Classifier: License :: OSI Approved :: GNU Affero General Public License v3
Classifier: Development Status :: 4 - Beta
Requires-Python: >=3.6
Requires-Dist: odoo14-addon-currency-rate-update
Requires-Dist: odoo <14.1dev,>=14.0a
